nodeping_api/__init__.py
nodeping_api/_query_nodeping_api.py
nodeping_api/_utils.py
nodeping_api/accounts.py
nodeping_api/check_token.py
nodeping_api/config.py
nodeping_api/contacts.py
nodeping_api/create_check.py
nodeping_api/delete_checks.py
nodeping_api/diagnostics.py
nodeping_api/disable_check.py
nodeping_api/get_checks.py
nodeping_api/group_contacts.py
nodeping_api/information.py
nodeping_api/maintenance.py
nodeping_api/notificationprofiles.py
nodeping_api/notifications.py
nodeping_api/results.py
nodeping_api/schedules.py
nodeping_api/update_checks.py
tests/__init__.py
tests/checks_1_test_get.py
tests/checks_2_test_create.py
tests/checks_3_test_update.py
tests/checks_4_test_disable.py
tests/checks_5_test_delete.py
tests/parameters.py
tests/test_accounts.py
tests/test_check_token.py
tests/test_contacts.py
tests/test_group_contacts.py
tests/test_information.py
tests/test_maintenance.py
tests/test_notifications.py
tests/test_results.py
tests/test_schedules.py
nodeping_api-1.8.0.dist-info/LICENSE
nodeping_api-1.8.0.dist-info/METADATA
nodeping_api-1.8.0.dist-info/WHEEL
nodeping_api-1.8.0.dist-info/top_level.txt
nodeping_api-1.8.0.dist-info/RECORD
