Metadata-Version: 2.1
Name: nodeping-api
Version: 1.8.0
Summary: Python package for querying the NodePing API
Home-page: https://github.com/NodePing/python-nodeping-api
Author: NodePing
Author-email: support@nodeping.com
Classifier: Programming Language :: Python :: 2.7
Classifier: Programming Language :: Python :: 3
Classifier: License :: OSI Approved :: MIT License
Classifier: Operating System :: OS Independent
License-File: LICENSE
